setup.py
yichun_shi_autocomplete/__init__.py
yichun_shi_autocomplete.egg-info/PKG-INFO
yichun_shi_autocomplete.egg-info/SOURCES.txt
yichun_shi_autocomplete.egg-info/dependency_links.txt
yichun_shi_autocomplete.egg-info/not-zip-safe
yichun_shi_autocomplete.egg-info/top_level.txt