Metadata-Version: 1.0
Name: yichun-shi-autocomplete
Version: 0.1
Summary: freakin awesome autocomplete system
Home-page: https://github.com/aliceshiyichun/yichun_shi_autocomplete
Author: Yichun Shi
Author-email: yichunsh@andrew.cmu.edu
License: CMU
Platform: UNKNOWN
